minisky/__init__.py
minisky-0.0.1.dist-info/METADATA
minisky-0.0.1.dist-info/WHEEL
minisky-0.0.1.dist-info/RECORD
